pytpch-0.2.0.dist-info/METADATA
pytpch-0.2.0.dist-info/WHEEL
pytpch-0.2.0.dist-info/license_files/LICENSE
pytpch-0.2.0.dist-info/license_files/LICENSE-TPC
pytpch/__init__.py
pytpch/pytpch.cpython-310-x86_64-linux-gnu.so
pytpch-0.2.0.dist-info/RECORD
