Metadata-Version: 2.1
Name: pytpch
Version: 0.2.0
Requires-Dist: pyarrow
Requires-Dist: black ==22.3.0 ; extra == 'dev'
Requires-Dist: pytest >=5.30 ; extra == 'dev'
Requires-Dist: pytest-xdist ; extra == 'dev'
Provides-Extra: dev
License-File: LICENSE
License-File: LICENSE-TPC
Summary: bindings to libdbgen / tpch-dbgen
Keywords: tpc-h
Author: Miles Granger <miles59923@gmail.com>
Author-email: Miles Granger <miles59923@gmail.com>
License: MIT
Requires-Python: >=3.8
Project-URL: homepage, https://github.com/milesgranger/pytpch
Project-URL: documentation, https://github.com/milesgranger/pytpch
Project-URL: repository, https://github.com/milesgranger/pytpch
